pydszoo/__init__.py
pydszoo/pde_utils.py
pydszoo/utils.py
pydszoo/allen_cahn/__init__.py
pydszoo/brusselator/__init__.py
pydszoo/fun/__init__.py
pydszoo/kardar_parisi_zhang/__init__.py
pydszoo/lorenz/__init__.py
pydszoo-0.0.1.dist-info/LICENSE
pydszoo-0.0.1.dist-info/METADATA
pydszoo-0.0.1.dist-info/WHEEL
pydszoo-0.0.1.dist-info/top_level.txt
pydszoo-0.0.1.dist-info/RECORD
